pytse_client/.gitignore
pytse_client/__init__.py
pytse_client/asks_bids.py
pytse_client/config.py
pytse_client/data/__init__.py
pytse_client/data/generate_indices_name.py
pytse_client/data/indices_name.json
pytse_client/data/symbols_name.json
pytse_client/download.py
pytse_client/examples/__init__.py
pytse_client/examples/client_types.py
pytse_client/examples/download_all.py
pytse_client/examples/download_financial_index.py
pytse_client/examples/download_financial_indexes.py
pytse_client/examples/download_shareholders_history.py
pytse_client/examples/download_shareholders_history_aync.py
pytse_client/examples/financial_index.py
pytse_client/examples/sma.py
pytse_client/examples/ticker.py
pytse_client/financial_index/__init__.py
pytse_client/financial_index/financial_index.py
pytse_client/historical_intraday/trade_details.py
pytse_client/orderbook/__init__.py
pytse_client/orderbook/common.py
pytse_client/orderbook/order_book.py
pytse_client/orderbook/order_book_async.py
pytse_client/proxy/dto.py
pytse_client/proxy/tsetmc.py
pytse_client/scraper/__init__.py
pytse_client/scraper/symbol_scraper.py
pytse_client/scraper/tsetmc_scraper.py
pytse_client/scripts/update_symbols_json.py
pytse_client/stats.py
pytse_client/symbols_data.py
pytse_client/ticker/__init__.py
pytse_client/ticker/api_extractors.py
pytse_client/ticker/dto.py
pytse_client/ticker/export.py
pytse_client/ticker/ticker.py
pytse_client/ticker_statisticals/README.md
pytse_client/ticker_statisticals/__init__.py
pytse_client/ticker_statisticals/generate_document.py
pytse_client/ticker_statisticals/key_stats.py
pytse_client/ticker_statisticals/utils.py
pytse_client/translations.py
pytse_client/tse_settings.py
pytse_client/utils/__init__.py
pytse_client/utils/async_utils.py
pytse_client/utils/date.py
pytse_client/utils/decorators.py
pytse_client/utils/logging_generator.py
pytse_client/utils/persian.py
pytse_client/utils/request_session.py
pytse_client/utils/scrape.py
pytse_client/utils/string.py
pytse_client-0.19.0.dist-info/LICENSE
pytse_client-0.19.0.dist-info/METADATA
pytse_client-0.19.0.dist-info/WHEEL
pytse_client-0.19.0.dist-info/RECORD
