Metadata-Version: 2.3
Name: pytse-client
Version: 0.19.0
Summary: tehran stock exchange(TSE) client in python
License: GPLv3
Author: glyphack
Author-email: sh.hooshyari@gmail.com
Requires-Python: >=3.7.2,<4.0.0
Classifier: License :: Other/Proprietary License
Classifier: Programming Language :: Python :: 3
Classifier: Programming Language :: Python :: 3.8
Classifier: Programming Language :: Python :: 3.9
Classifier: Programming Language :: Python :: 3.10
Classifier: Programming Language :: Python :: 3.11
Classifier: Programming Language :: Python :: 3.12
Classifier: Programming Language :: Python :: 3.13
Requires-Dist: aiohttp (>=3.7.4,<4.0.0)
Requires-Dist: beautifulsoup4 (>=4.9.3,<5.0.0)
Requires-Dist: black (>=22.6.0,<23.0.0)
Requires-Dist: jdatetime (>=3.6.2,<4.0.0)
Requires-Dist: lxml (>=4.6.3,<5.0.0)
Requires-Dist: pandas
Requires-Dist: requests (>=2.23.0,<3.0.0)
Requires-Dist: tenacity (>=7.0.0,<8.0.0)
